.gitignore
.travis.yml
CHANGES.rst
LICENSE
MANIFEST.in
README.rst
flake8_oist_steps.py
requirements-dev.txt
requirements.txt
run_tests.py
setup.cfg
setup.py
tox.ini
flake8_oist_steps.egg-info/PKG-INFO
flake8_oist_steps.egg-info/SOURCES.txt
flake8_oist_steps.egg-info/dependency_links.txt
flake8_oist_steps.egg-info/entry_points.txt
flake8_oist_steps.egg-info/not-zip-safe
flake8_oist_steps.egg-info/requires.txt
flake8_oist_steps.egg-info/top_level.txt